greenthread/green.py
greenthread/green_eventlet.py
greenthread/green_gevent.py
greenthread/monkey.py
greenthread/patch_gevent_grpc.py
greenthread-0.1.1.dist-info/LICENSE
greenthread-0.1.1.dist-info/METADATA
greenthread-0.1.1.dist-info/WHEEL
greenthread-0.1.1.dist-info/top_level.txt
greenthread-0.1.1.dist-info/RECORD
