Metadata-Version: 2.1
Name: greenthread
Version: 0.1.1
Summary: A simple green thread library compatible eventlet and gevent
Home-page: https://github.com/tsinghtech-research/greenthread
Author: tsinghtech
Author-email: vision@qingtong.cn
Classifier: Programming Language :: Python :: 3
Classifier: License :: OSI Approved :: Apache Software License
Classifier: Operating System :: OS Independent
Requires-Python: >=3.7
License-File: LICENSE
